autodox/__init__.py
autodox/functions.py
autodox-0.1.16.dist-info/METADATA
autodox-0.1.16.dist-info/WHEEL
autodox-0.1.16.dist-info/entry_points.txt
autodox-0.1.16.dist-info/RECORD
