Metadata-Version: 2.1
Name: autodox
Version: 0.1.16
Summary: Tool for generating documentation automatically from code annotations, types, and docstrings.
Project-URL: Homepage, https://github.com/k98kurz/autodox
Project-URL: Bug Tracker, https://github.com/k98kurz/autodox/issues
Author-email: k98kurz <k98kurz@gmail.com>
Classifier: Development Status :: 3 - Alpha
Classifier: License :: OSI Approved :: ISC License (ISCL)
Classifier: Operating System :: OS Independent
Classifier: Programming Language :: Python :: 3
Classifier: Topic :: Documentation
Requires-Python: >=3.10
